{
    "Firefox": "firefox",
    "Code": "code",
    "chromium-browser": "chrome",
    "chrome": "chrome",
    "google-chrome": "chrome",
    "Blueman-manager": "bluetooth",
    "Display-im": "image",
    "x-terminal-emulator": "terminal",
    "Xfce4-terminal": "terminal",
    "keepassxc": "key",
    "thunderbird": "envelope",
    "jetbrains-idea-ce": "edit",
    "nautilus": "folder-open",
    "Thunar": "folder-open",
    "clementine": "music",
    "vlc": "play",
    "Mate-calc": "calculator",
    "signal": "comment",
    "bsnes": "gamepad",
    "Lsnes": "gamepad"
}

